{"type":"FeatureCollection","bbox":[0.0,0.0,-1.0,-1.0],"features":[{"type":"Feature","properties":{"lga_name11":"Alpine (S)","b40":114,"lga_code_2011":20110,"b60":null},"id":"lga_vic_crime_statistics_2012_2016.fid--38e292b1_16a853dde5d_-38a2"},{"type":"Feature","properties":{"lga_name11":"Ararat (RC)","b40":275,"lga_code_2011":20260,"b60":null},"id":"lga_vic_crime_statistics_2012_2016.fid--38e292b1_16a853dde5d_-38a1"},{"type":"Feature","properties":{"lga_name11":"Ballarat (C)","b40":3127,"lga_code_2011":20570,"b60":1},"id":"lga_vic_crime_statistics_2012_2016.fid--38e292b1_16a853dde5d_-38a0"},{"type":"Feature","properties":{"lga_name11":"Banyule (C)","b40":2169,"lga_code_2011":20660,"b60":null},"id":"lga_vic_crime_statistics_2012_2016.fid--38e292b1_16a853dde5d_-389f"},{"type":"Feature","properties":{"lga_name11":"Bass Coast (S)","b40":565,"lga_code_2011":20740,"b60":null},"id":"lga_vic_crime_statistics_2012_2016.fid--38e292b1_16a853dde5d_-389e"},{"type":"Feature","properties":{"lga_name11":"Baw Baw (S)","b40":793,"lga_code_2011":20830,"b60":null},"id":"lga_vic_crime_statistics_2012_2016.fid--38e292b1_16a853dde5d_-389d"},{"type":"Feature","properties":{"lga_name11":"Bayside (C)","b40":1693,"lga_code_2011":20910,"b60":null},"id":"lga_vic_crime_statistics_2012_2016.fid--38e292b1_16a853dde5d_-389c"},{"type":"Feature","properties":{"lga_name11":"Benalla (RC)","b40":239,"lga_code_2011":21010,"b60":1},"id":"lga_vic_crime_statistics_2012_2016.fid--38e292b1_16a853dde5d_-389b"},{"type":"Feature","properties":{"lga_name11":"Boroondara (C)","b40":2673,"lga_code_2011":21110,"b60":null},"id":"lga_vic_crime_statistics_2012_2016.fid--38e292b1_16a853dde5d_-389a"},{"type":"Feature","properties":{"lga_name11":"Brimbank (C)","b40":7398,"lga_code_2011":21180,"b60":1},"id":"lga_vic_crime_statistics_2012_2016.fid--38e292b1_16a853dde5d_-3899"},{"type":"Feature","properties":{"lga_name11":"Buloke (S)","b40":92,"lga_code_2011":21270,"b60":null},"id":"lga_vic_crime_statistics_2012_2016.fid--38e292b1_16a853dde5d_-3898"},{"type":"Feature","properties":{"lga_name11":"Campaspe (S)","b40":866,"lga_code_2011":21370,"b60":null},"id":"lga_vic_crime_statistics_2012_2016.fid--38e292b1_16a853dde5d_-3897"},{"type":"Feature","properties":{"lga_name11":"Cardinia (S)","b40":1522,"lga_code_2011":21450,"b60":null},"id":"lga_vic_crime_statistics_2012_2016.fid--38e292b1_16a853dde5d_-3896"},{"type":"Feature","properties":{"lga_name11":"Casey (C)","b40":4689,"lga_code_2011":21610,"b60":null},"id":"lga_vic_crime_statistics_2012_2016.fid--38e292b1_16a853dde5d_-3895"},{"type":"Feature","properties":{"lga_name11":"Central Goldfields (S)","b40":202,"lga_code_2011":21670,"b60":null},"id":"lga_vic_crime_statistics_2012_2016.fid--38e292b1_16a853dde5d_-3894"},{"type":"Feature","properties":{"lga_name11":"Colac-Otway (S)","b40":364,"lga_code_2011":21750,"b60":null},"id":"lga_vic_crime_statistics_2012_2016.fid--38e292b1_16a853dde5d_-3893"},{"type":"Feature","properties":{"lga_name11":"Corangamite (S)","b40":194,"lga_code_2011":21830,"b60":null},"id":"lga_vic_crime_statistics_2012_2016.fid--38e292b1_16a853dde5d_-3892"},{"type":"Feature","properties":{"lga_name11":"Darebin (C)","b40":5008,"lga_code_2011":21890,"b60":4},"id":"lga_vic_crime_statistics_2012_2016.fid--38e292b1_16a853dde5d_-3891"},{"type":"Feature","properties":{"lga_name11":"East Gippsland (S)","b40":795,"lga_code_2011":22110,"b60":null},"id":"lga_vic_crime_statistics_2012_2016.fid--38e292b1_16a853dde5d_-3890"},{"type":"Feature","properties":{"lga_name11":"Frankston (C)","b40":3879,"lga_code_2011":22170,"b60":null},"id":"lga_vic_crime_statistics_2012_2016.fid--38e292b1_16a853dde5d_-388f"},{"type":"Feature","properties":{"lga_name11":"Gannawarra (S)","b40":109,"lga_code_2011":22250,"b60":null},"id":"lga_vic_crime_statistics_2012_2016.fid--38e292b1_16a853dde5d_-388e"},{"type":"Feature","properties":{"lga_name11":"Golden Plains (S)","b40":122,"lga_code_2011":22490,"b60":null},"id":"lga_vic_crime_statistics_2012_2016.fid--38e292b1_16a853dde5d_-388d"},{"type":"Feature","properties":{"lga_name11":"Greater Bendigo (C)","b40":2078,"lga_code_2011":22620,"b60":null},"id":"lga_vic_crime_statistics_2012_2016.fid--38e292b1_16a853dde5d_-388c"},{"type":"Feature","properties":{"lga_name11":"Greater Dandenong (C)","b40":4414,"lga_code_2011":22670,"b60":null},"id":"lga_vic_crime_statistics_2012_2016.fid--38e292b1_16a853dde5d_-388b"},{"type":"Feature","properties":{"lga_name11":"Greater Geelong (C)","b40":5986,"lga_code_2011":22750,"b60":1},"id":"lga_vic_crime_statistics_2012_2016.fid--38e292b1_16a853dde5d_-388a"},{"type":"Feature","properties":{"lga_name11":"Greater Shepparton (C)","b40":1705,"lga_code_2011":22830,"b60":null},"id":"lga_vic_crime_statistics_2012_2016.fid--38e292b1_16a853dde5d_-3889"},{"type":"Feature","properties":{"lga_name11":"Hepburn (S)","b40":213,"lga_code_2011":22910,"b60":null},"id":"lga_vic_crime_statistics_2012_2016.fid--38e292b1_16a853dde5d_-3888"},{"type":"Feature","properties":{"lga_name11":"Hindmarsh (S)","b40":51,"lga_code_2011":22980,"b60":null},"id":"lga_vic_crime_statistics_2012_2016.fid--38e292b1_16a853dde5d_-3887"},{"type":"Feature","properties":{"lga_name11":"Hobsons Bay (C)","b40":2988,"lga_code_2011":23110,"b60":null},"id":"lga_vic_crime_statistics_2012_2016.fid--38e292b1_16a853dde5d_-3886"},{"type":"Feature","properties":{"lga_name11":"Horsham (RC)","b40":462,"lga_code_2011":23190,"b60":null},"id":"lga_vic_crime_statistics_2012_2016.fid--38e292b1_16a853dde5d_-3885"},{"type":"Feature","properties":{"lga_name11":"Hume (C)","b40":5173,"lga_code_2011":23270,"b60":null},"id":"lga_vic_crime_statistics_2012_2016.fid--38e292b1_16a853dde5d_-3884"},{"type":"Feature","properties":{"lga_name11":"Indigo (S)","b40":170,"lga_code_2011":23350,"b60":null},"id":"lga_vic_crime_statistics_2012_2016.fid--38e292b1_16a853dde5d_-3883"},{"type":"Feature","properties":{"lga_name11":"Kingston (C)","b40":3384,"lga_code_2011":23430,"b60":null},"id":"lga_vic_crime_statistics_2012_2016.fid--38e292b1_16a853dde5d_-3882"},{"type":"Feature","properties":{"lga_name11":"Knox (C)","b40":3296,"lga_code_2011":23670,"b60":null},"id":"lga_vic_crime_statistics_2012_2016.fid--38e292b1_16a853dde5d_-3881"},{"type":"Feature","properties":{"lga_name11":"Latrobe (C)","b40":2247,"lga_code_2011":23810,"b60":null},"id":"lga_vic_crime_statistics_2012_2016.fid--38e292b1_16a853dde5d_-3880"},{"type":"Feature","properties":{"lga_name11":"Loddon (S)","b40":109,"lga_code_2011":23940,"b60":null},"id":"lga_vic_crime_statistics_2012_2016.fid--38e292b1_16a853dde5d_-387f"},{"type":"Feature","properties":{"lga_name11":"Macedon Ranges (S)","b40":464,"lga_code_2011":24130,"b60":null},"id":"lga_vic_crime_statistics_2012_2016.fid--38e292b1_16a853dde5d_-387e"},{"type":"Feature","properties":{"lga_name11":"Manningham (C)","b40":1568,"lga_code_2011":24210,"b60":1},"id":"lga_vic_crime_statistics_2012_2016.fid--38e292b1_16a853dde5d_-387d"},{"type":"Feature","properties":{"lga_name11":"Glen Eira (C)","b40":2131,"lga_code_2011":22310,"b60":1},"id":"lga_vic_crime_statistics_2012_2016.fid--38e292b1_16a853dde5d_-387c"},{"type":"Feature","properties":{"lga_name11":"Glenelg (S)","b40":371,"lga_code_2011":22410,"b60":null},"id":"lga_vic_crime_statistics_2012_2016.fid--38e292b1_16a853dde5d_-387b"},{"type":"Feature","properties":{"lga_name11":"Mansfield (S)","b40":139,"lga_code_2011":24250,"b60":null},"id":"lga_vic_crime_statistics_2012_2016.fid--38e292b1_16a853dde5d_-387a"},{"type":"Feature","properties":{"lga_name11":"Maribyrnong (C)","b40":3994,"lga_code_2011":24330,"b60":null},"id":"lga_vic_crime_statistics_2012_2016.fid--38e292b1_16a853dde5d_-3879"},{"type":"Feature","properties":{"lga_name11":"Maroondah (C)","b40":2182,"lga_code_2011":24410,"b60":null},"id":"lga_vic_crime_statistics_2012_2016.fid--38e292b1_16a853dde5d_-3878"},{"type":"Feature","properties":{"lga_name11":"Melbourne (C)","b40":11319,"lga_code_2011":24600,"b60":3},"id":"lga_vic_crime_statistics_2012_2016.fid--38e292b1_16a853dde5d_-3877"},{"type":"Feature","properties":{"lga_name11":"Melton (S)","b40":2978,"lga_code_2011":24650,"b60":null},"id":"lga_vic_crime_statistics_2012_2016.fid--38e292b1_16a853dde5d_-3876"},{"type":"Feature","properties":{"lga_name11":"Mildura (RC)","b40":1439,"lga_code_2011":24780,"b60":null},"id":"lga_vic_crime_statistics_2012_2016.fid--38e292b1_16a853dde5d_-3875"},{"type":"Feature","properties":{"lga_name11":"Mitchell (S)","b40":566,"lga_code_2011":24850,"b60":null},"id":"lga_vic_crime_statistics_2012_2016.fid--38e292b1_16a853dde5d_-3874"},{"type":"Feature","properties":{"lga_name11":"Moira (S)","b40":416,"lga_code_2011":24900,"b60":null},"id":"lga_vic_crime_statistics_2012_2016.fid--38e292b1_16a853dde5d_-3873"},{"type":"Feature","properties":{"lga_name11":"Monash (C)","b40":3787,"lga_code_2011":24970,"b60":null},"id":"lga_vic_crime_statistics_2012_2016.fid--38e292b1_16a853dde5d_-3872"},{"type":"Feature","properties":{"lga_name11":"Moonee Valley (C)","b40":3150,"lga_code_2011":25060,"b60":1},"id":"lga_vic_crime_statistics_2012_2016.fid--38e292b1_16a853dde5d_-3871"},{"type":"Feature","properties":{"lga_name11":"Moorabool (S)","b40":577,"lga_code_2011":25150,"b60":null},"id":"lga_vic_crime_statistics_2012_2016.fid--38e292b1_16a853dde5d_-3870"},{"type":"Feature","properties":{"lga_name11":"Moreland (C)","b40":4957,"lga_code_2011":25250,"b60":null},"id":"lga_vic_crime_statistics_2012_2016.fid--38e292b1_16a853dde5d_-386f"},{"type":"Feature","properties":{"lga_name11":"Mornington Peninsula (S)","b40":3024,"lga_code_2011":25340,"b60":null},"id":"lga_vic_crime_statistics_2012_2016.fid--38e292b1_16a853dde5d_-386e"},{"type":"Feature","properties":{"lga_name11":"Mount Alexander (S)","b40":213,"lga_code_2011":25430,"b60":null},"id":"lga_vic_crime_statistics_2012_2016.fid--38e292b1_16a853dde5d_-386d"},{"type":"Feature","properties":{"lga_name11":"Moyne (S)","b40":257,"lga_code_2011":25490,"b60":null},"id":"lga_vic_crime_statistics_2012_2016.fid--38e292b1_16a853dde5d_-386c"},{"type":"Feature","properties":{"lga_name11":"Murrindindi (S)","b40":154,"lga_code_2011":25620,"b60":null},"id":"lga_vic_crime_statistics_2012_2016.fid--38e292b1_16a853dde5d_-386b"},{"type":"Feature","properties":{"lga_name11":"Nillumbik (S)","b40":497,"lga_code_2011":25710,"b60":null},"id":"lga_vic_crime_statistics_2012_2016.fid--38e292b1_16a853dde5d_-386a"},{"type":"Feature","properties":{"lga_name11":"Northern Grampians (S)","b40":192,"lga_code_2011":25810,"b60":null},"id":"lga_vic_crime_statistics_2012_2016.fid--38e292b1_16a853dde5d_-3869"},{"type":"Feature","properties":{"lga_name11":"Port Phillip (C)","b40":3661,"lga_code_2011":25900,"b60":null},"id":"lga_vic_crime_statistics_2012_2016.fid--38e292b1_16a853dde5d_-3868"},{"type":"Feature","properties":{"lga_name11":"Pyrenees (S)","b40":78,"lga_code_2011":25990,"b60":null},"id":"lga_vic_crime_statistics_2012_2016.fid--38e292b1_16a853dde5d_-3867"},{"type":"Feature","properties":{"lga_name11":"Queenscliffe (B)","b40":57,"lga_code_2011":26080,"b60":null},"id":"lga_vic_crime_statistics_2012_2016.fid--38e292b1_16a853dde5d_-3866"},{"type":"Feature","properties":{"lga_name11":"South Gippsland (S)","b40":306,"lga_code_2011":26170,"b60":null},"id":"lga_vic_crime_statistics_2012_2016.fid--38e292b1_16a853dde5d_-3865"},{"type":"Feature","properties":{"lga_name11":"Southern Grampians (S)","b40":251,"lga_code_2011":26260,"b60":null},"id":"lga_vic_crime_statistics_2012_2016.fid--38e292b1_16a853dde5d_-3864"},{"type":"Feature","properties":{"lga_name11":"Stonnington (C)","b40":3543,"lga_code_2011":26350,"b60":null},"id":"lga_vic_crime_statistics_2012_2016.fid--38e292b1_16a853dde5d_-3863"},{"type":"Feature","properties":{"lga_name11":"Strathbogie (S)","b40":145,"lga_code_2011":26430,"b60":null},"id":"lga_vic_crime_statistics_2012_2016.fid--38e292b1_16a853dde5d_-3862"},{"type":"Feature","properties":{"lga_name11":"Surf Coast (S)","b40":544,"lga_code_2011":26490,"b60":null},"id":"lga_vic_crime_statistics_2012_2016.fid--38e292b1_16a853dde5d_-3861"},{"type":"Feature","properties":{"lga_name11":"Swan Hill (RC)","b40":423,"lga_code_2011":26610,"b60":null},"id":"lga_vic_crime_statistics_2012_2016.fid--38e292b1_16a853dde5d_-3860"},{"type":"Feature","properties":{"lga_name11":"Towong (S)","b40":69,"lga_code_2011":26670,"b60":null},"id":"lga_vic_crime_statistics_2012_2016.fid--38e292b1_16a853dde5d_-385f"},{"type":"Feature","properties":{"lga_name11":"Wangaratta (RC)","b40":557,"lga_code_2011":26700,"b60":null},"id":"lga_vic_crime_statistics_2012_2016.fid--38e292b1_16a853dde5d_-385e"},{"type":"Feature","properties":{"lga_name11":"Warrnambool (C)","b40":449,"lga_code_2011":26730,"b60":null},"id":"lga_vic_crime_statistics_2012_2016.fid--38e292b1_16a853dde5d_-385d"},{"type":"Feature","properties":{"lga_name11":"Wellington (S)","b40":807,"lga_code_2011":26810,"b60":null},"id":"lga_vic_crime_statistics_2012_2016.fid--38e292b1_16a853dde5d_-385c"},{"type":"Feature","properties":{"lga_name11":"West Wimmera (S)","b40":26,"lga_code_2011":26890,"b60":null},"id":"lga_vic_crime_statistics_2012_2016.fid--38e292b1_16a853dde5d_-385b"},{"type":"Feature","properties":{"lga_name11":"Whitehorse (C)","b40":2753,"lga_code_2011":26980,"b60":2},"id":"lga_vic_crime_statistics_2012_2016.fid--38e292b1_16a853dde5d_-385a"},{"type":"Feature","properties":{"lga_name11":"Whittlesea (C)","b40":4839,"lga_code_2011":27070,"b60":1},"id":"lga_vic_crime_statistics_2012_2016.fid--38e292b1_16a853dde5d_-3859"},{"type":"Feature","properties":{"lga_name11":"Wodonga (RC)","b40":1077,"lga_code_2011":27170,"b60":null},"id":"lga_vic_crime_statistics_2012_2016.fid--38e292b1_16a853dde5d_-3858"},{"type":"Feature","properties":{"lga_name11":"Wyndham (C)","b40":5446,"lga_code_2011":27260,"b60":null},"id":"lga_vic_crime_statistics_2012_2016.fid--38e292b1_16a853dde5d_-3857"},{"type":"Feature","properties":{"lga_name11":"Yarra (C)","b40":4505,"lga_code_2011":27350,"b60":60},"id":"lga_vic_crime_statistics_2012_2016.fid--38e292b1_16a853dde5d_-3856"},{"type":"Feature","properties":{"lga_name11":"Yarra Ranges (S)","b40":2049,"lga_code_2011":27450,"b60":null},"id":"lga_vic_crime_statistics_2012_2016.fid--38e292b1_16a853dde5d_-3855"},{"type":"Feature","properties":{"lga_name11":"Yarriambiack (S)","b40":105,"lga_code_2011":27630,"b60":null},"id":"lga_vic_crime_statistics_2012_2016.fid--38e292b1_16a853dde5d_-3854"},{"type":"Feature","properties":{"lga_name11":"Alpine (S)","b40":109,"lga_code_2011":20110,"b60":null},"id":"lga_vic_crime_statistics_2012_2016.fid--38e292b1_16a853dde5d_-3853"},{"type":"Feature","properties":{"lga_name11":"Ararat (RC)","b40":208,"lga_code_2011":20260,"b60":null},"id":"lga_vic_crime_statistics_2012_2016.fid--38e292b1_16a853dde5d_-3852"},{"type":"Feature","properties":{"lga_name11":"Ballarat (C)","b40":3313,"lga_code_2011":20570,"b60":null},"id":"lga_vic_crime_statistics_2012_2016.fid--38e292b1_16a853dde5d_-3851"},{"type":"Feature","properties":{"lga_name11":"Banyule (C)","b40":3197,"lga_code_2011":20660,"b60":null},"id":"lga_vic_crime_statistics_2012_2016.fid--38e292b1_16a853dde5d_-3850"},{"type":"Feature","properties":{"lga_name11":"Bass Coast (S)","b40":518,"lga_code_2011":20740,"b60":null},"id":"lga_vic_crime_statistics_2012_2016.fid--38e292b1_16a853dde5d_-384f"},{"type":"Feature","properties":{"lga_name11":"Baw Baw (S)","b40":802,"lga_code_2011":20830,"b60":null},"id":"lga_vic_crime_statistics_2012_2016.fid--38e292b1_16a853dde5d_-384e"},{"type":"Feature","properties":{"lga_name11":"Bayside (C)","b40":1423,"lga_code_2011":20910,"b60":null},"id":"lga_vic_crime_statistics_2012_2016.fid--38e292b1_16a853dde5d_-384d"},{"type":"Feature","properties":{"lga_name11":"Benalla (RC)","b40":212,"lga_code_2011":21010,"b60":1},"id":"lga_vic_crime_statistics_2012_2016.fid--38e292b1_16a853dde5d_-384c"},{"type":"Feature","properties":{"lga_name11":"Boroondara (C)","b40":2693,"lga_code_2011":21110,"b60":null},"id":"lga_vic_crime_statistics_2012_2016.fid--38e292b1_16a853dde5d_-384b"},{"type":"Feature","properties":{"lga_name11":"Brimbank (C)","b40":7387,"lga_code_2011":21180,"b60":1},"id":"lga_vic_crime_statistics_2012_2016.fid--38e292b1_16a853dde5d_-384a"},{"type":"Feature","properties":{"lga_name11":"Buloke (S)","b40":80,"lga_code_2011":21270,"b60":null},"id":"lga_vic_crime_statistics_2012_2016.fid--38e292b1_16a853dde5d_-3849"},{"type":"Feature","properties":{"lga_name11":"Campaspe (S)","b40":878,"lga_code_2011":21370,"b60":null},"id":"lga_vic_crime_statistics_2012_2016.fid--38e292b1_16a853dde5d_-3848"},{"type":"Feature","properties":{"lga_name11":"Cardinia (S)","b40":1755,"lga_code_2011":21450,"b60":null},"id":"lga_vic_crime_statistics_2012_2016.fid--38e292b1_16a853dde5d_-3847"},{"type":"Feature","properties":{"lga_name11":"Casey (C)","b40":4954,"lga_code_2011":21610,"b60":null},"id":"lga_vic_crime_statistics_2012_2016.fid--38e292b1_16a853dde5d_-3846"},{"type":"Feature","properties":{"lga_name11":"Central Goldfields (S)","b40":180,"lga_code_2011":21670,"b60":null},"id":"lga_vic_crime_statistics_2012_2016.fid--38e292b1_16a853dde5d_-3845"},{"type":"Feature","properties":{"lga_name11":"Colac-Otway (S)","b40":305,"lga_code_2011":21750,"b60":null},"id":"lga_vic_crime_statistics_2012_2016.fid--38e292b1_16a853dde5d_-3844"},{"type":"Feature","properties":{"lga_name11":"Corangamite (S)","b40":134,"lga_code_2011":21830,"b60":null},"id":"lga_vic_crime_statistics_2012_2016.fid--38e292b1_16a853dde5d_-3843"},{"type":"Feature","properties":{"lga_name11":"Darebin (C)","b40":4270,"lga_code_2011":21890,"b60":1},"id":"lga_vic_crime_statistics_2012_2016.fid--38e292b1_16a853dde5d_-3842"},{"type":"Feature","properties":{"lga_name11":"East Gippsland (S)","b40":1092,"lga_code_2011":22110,"b60":null},"id":"lga_vic_crime_statistics_2012_2016.fid--38e292b1_16a853dde5d_-3841"},{"type":"Feature","properties":{"lga_name11":"Frankston (C)","b40":4332,"lga_code_2011":22170,"b60":null},"id":"lga_vic_crime_statistics_2012_2016.fid--38e292b1_16a853dde5d_-3840"},{"type":"Feature","properties":{"lga_name11":"Gannawarra (S)","b40":122,"lga_code_2011":22250,"b60":null},"id":"lga_vic_crime_statistics_2012_2016.fid--38e292b1_16a853dde5d_-383f"},{"type":"Feature","properties":{"lga_name11":"Golden Plains (S)","b40":119,"lga_code_2011":22490,"b60":null},"id":"lga_vic_crime_statistics_2012_2016.fid--38e292b1_16a853dde5d_-383e"},{"type":"Feature","properties":{"lga_name11":"Greater Bendigo (C)","b40":2000,"lga_code_2011":22620,"b60":null},"id":"lga_vic_crime_statistics_2012_2016.fid--38e292b1_16a853dde5d_-383d"},{"type":"Feature","properties":{"lga_name11":"Greater Dandenong (C)","b40":4892,"lga_code_2011":22670,"b60":null},"id":"lga_vic_crime_statistics_2012_2016.fid--38e292b1_16a853dde5d_-383c"},{"type":"Feature","properties":{"lga_name11":"Greater Geelong (C)","b40":5811,"lga_code_2011":22750,"b60":null},"id":"lga_vic_crime_statistics_2012_2016.fid--38e292b1_16a853dde5d_-383b"},{"type":"Feature","properties":{"lga_name11":"Greater Shepparton (C)","b40":1490,"lga_code_2011":22830,"b60":null},"id":"lga_vic_crime_statistics_2012_2016.fid--38e292b1_16a853dde5d_-383a"},{"type":"Feature","properties":{"lga_name11":"Hepburn (S)","b40":177,"lga_code_2011":22910,"b60":null},"id":"lga_vic_crime_statistics_2012_2016.fid--38e292b1_16a853dde5d_-3839"},{"type":"Feature","properties":{"lga_name11":"Hindmarsh (S)","b40":68,"lga_code_2011":22980,"b60":null},"id":"lga_vic_crime_statistics_2012_2016.fid--38e292b1_16a853dde5d_-3838"},{"type":"Feature","properties":{"lga_name11":"Hobsons Bay (C)","b40":2676,"lga_code_2011":23110,"b60":2},"id":"lga_vic_crime_statistics_2012_2016.fid--38e292b1_16a853dde5d_-3837"},{"type":"Feature","properties":{"lga_name11":"Horsham (RC)","b40":1221,"lga_code_2011":23190,"b60":null},"id":"lga_vic_crime_statistics_2012_2016.fid--38e292b1_16a853dde5d_-3836"},{"type":"Feature","properties":{"lga_name11":"Hume (C)","b40":4932,"lga_code_2011":23270,"b60":null},"id":"lga_vic_crime_statistics_2012_2016.fid--38e292b1_16a853dde5d_-3835"},{"type":"Feature","properties":{"lga_name11":"Indigo (S)","b40":167,"lga_code_2011":23350,"b60":null},"id":"lga_vic_crime_statistics_2012_2016.fid--38e292b1_16a853dde5d_-3834"},{"type":"Feature","properties":{"lga_name11":"Kingston (C)","b40":3209,"lga_code_2011":23430,"b60":null},"id":"lga_vic_crime_statistics_2012_2016.fid--38e292b1_16a853dde5d_-3833"},{"type":"Feature","properties":{"lga_name11":"Knox (C)","b40":3595,"lga_code_2011":23670,"b60":null},"id":"lga_vic_crime_statistics_2012_2016.fid--38e292b1_16a853dde5d_-3832"},{"type":"Feature","properties":{"lga_name11":"Latrobe (C)","b40":2363,"lga_code_2011":23810,"b60":1},"id":"lga_vic_crime_statistics_2012_2016.fid--38e292b1_16a853dde5d_-3831"},{"type":"Feature","properties":{"lga_name11":"Loddon (S)","b40":125,"lga_code_2011":23940,"b60":null},"id":"lga_vic_crime_statistics_2012_2016.fid--38e292b1_16a853dde5d_-3830"},{"type":"Feature","properties":{"lga_name11":"Macedon Ranges (S)","b40":473,"lga_code_2011":24130,"b60":null},"id":"lga_vic_crime_statistics_2012_2016.fid--38e292b1_16a853dde5d_-382f"},{"type":"Feature","properties":{"lga_name11":"Glen Eira (C)","b40":2078,"lga_code_2011":22310,"b60":1},"id":"lga_vic_crime_statistics_2012_2016.fid--38e292b1_16a853dde5d_-382e"},{"type":"Feature","properties":{"lga_name11":"Glenelg (S)","b40":414,"lga_code_2011":22410,"b60":null},"id":"lga_vic_crime_statistics_2012_2016.fid--38e292b1_16a853dde5d_-382d"},{"type":"Feature","properties":{"lga_name11":"Manningham (C)","b40":1434,"lga_code_2011":24210,"b60":null},"id":"lga_vic_crime_statistics_2012_2016.fid--38e292b1_16a853dde5d_-382c"},{"type":"Feature","properties":{"lga_name11":"Mansfield (S)","b40":136,"lga_code_2011":24250,"b60":null},"id":"lga_vic_crime_statistics_2012_2016.fid--38e292b1_16a853dde5d_-382b"},{"type":"Feature","properties":{"lga_name11":"Maribyrnong (C)","b40":3508,"lga_code_2011":24330,"b60":2},"id":"lga_vic_crime_statistics_2012_2016.fid--38e292b1_16a853dde5d_-382a"},{"type":"Feature","properties":{"lga_name11":"Maroondah (C)","b40":1981,"lga_code_2011":24410,"b60":null},"id":"lga_vic_crime_statistics_2012_2016.fid--38e292b1_16a853dde5d_-3829"},{"type":"Feature","properties":{"lga_name11":"Melbourne (C)","b40":12549,"lga_code_2011":24600,"b60":null},"id":"lga_vic_crime_statistics_2012_2016.fid--38e292b1_16a853dde5d_-3828"},{"type":"Feature","properties":{"lga_name11":"Melton (S)","b40":2812,"lga_code_2011":24650,"b60":null},"id":"lga_vic_crime_statistics_2012_2016.fid--38e292b1_16a853dde5d_-3827"},{"type":"Feature","properties":{"lga_name11":"Mildura (RC)","b40":1366,"lga_code_2011":24780,"b60":null},"id":"lga_vic_crime_statistics_2012_2016.fid--38e292b1_16a853dde5d_-3826"},{"type":"Feature","properties":{"lga_name11":"Mitchell (S)","b40":652,"lga_code_2011":24850,"b60":null},"id":"lga_vic_crime_statistics_2012_2016.fid--38e292b1_16a853dde5d_-3825"},{"type":"Feature","properties":{"lga_name11":"Moira (S)","b40":404,"lga_code_2011":24900,"b60":null},"id":"lga_vic_crime_statistics_2012_2016.fid--38e292b1_16a853dde5d_-3824"},{"type":"Feature","properties":{"lga_name11":"Monash (C)","b40":3625,"lga_code_2011":24970,"b60":1},"id":"lga_vic_crime_statistics_2012_2016.fid--38e292b1_16a853dde5d_-3823"},{"type":"Feature","properties":{"lga_name11":"Moonee Valley (C)","b40":3007,"lga_code_2011":25060,"b60":null},"id":"lga_vic_crime_statistics_2012_2016.fid--38e292b1_16a853dde5d_-3822"},{"type":"Feature","properties":{"lga_name11":"Moorabool (S)","b40":619,"lga_code_2011":25150,"b60":null},"id":"lga_vic_crime_statistics_2012_2016.fid--38e292b1_16a853dde5d_-3821"},{"type":"Feature","properties":{"lga_name11":"Moreland (C)","b40":4526,"lga_code_2011":25250,"b60":null},"id":"lga_vic_crime_statistics_2012_2016.fid--38e292b1_16a853dde5d_-3820"},{"type":"Feature","properties":{"lga_name11":"Mornington Peninsula (S)","b40":2979,"lga_code_2011":25340,"b60":null},"id":"lga_vic_crime_statistics_2012_2016.fid--38e292b1_16a853dde5d_-381f"},{"type":"Feature","properties":{"lga_name11":"Mount Alexander (S)","b40":254,"lga_code_2011":25430,"b60":null},"id":"lga_vic_crime_statistics_2012_2016.fid--38e292b1_16a853dde5d_-381e"},{"type":"Feature","properties":{"lga_name11":"Moyne (S)","b40":214,"lga_code_2011":25490,"b60":null},"id":"lga_vic_crime_statistics_2012_2016.fid--38e292b1_16a853dde5d_-381d"},{"type":"Feature","properties":{"lga_name11":"Murrindindi (S)","b40":155,"lga_code_2011":25620,"b60":null},"id":"lga_vic_crime_statistics_2012_2016.fid--38e292b1_16a853dde5d_-381c"},{"type":"Feature","properties":{"lga_name11":"Nillumbik (S)","b40":589,"lga_code_2011":25710,"b60":null},"id":"lga_vic_crime_statistics_2012_2016.fid--38e292b1_16a853dde5d_-381b"},{"type":"Feature","properties":{"lga_name11":"Northern Grampians (S)","b40":163,"lga_code_2011":25810,"b60":null},"id":"lga_vic_crime_statistics_2012_2016.fid--38e292b1_16a853dde5d_-381a"},{"type":"Feature","properties":{"lga_name11":"Port Phillip (C)","b40":4365,"lga_code_2011":25900,"b60":2},"id":"lga_vic_crime_statistics_2012_2016.fid--38e292b1_16a853dde5d_-3819"},{"type":"Feature","properties":{"lga_name11":"Pyrenees (S)","b40":87,"lga_code_2011":25990,"b60":null},"id":"lga_vic_crime_statistics_2012_2016.fid--38e292b1_16a853dde5d_-3818"},{"type":"Feature","properties":{"lga_name11":"Queenscliffe (B)","b40":40,"lga_code_2011":26080,"b60":null},"id":"lga_vic_crime_statistics_2012_2016.fid--38e292b1_16a853dde5d_-3817"},{"type":"Feature","properties":{"lga_name11":"South Gippsland (S)","b40":502,"lga_code_2011":26170,"b60":null},"id":"lga_vic_crime_statistics_2012_2016.fid--38e292b1_16a853dde5d_-3816"},{"type":"Feature","properties":{"lga_name11":"Southern Grampians (S)","b40":228,"lga_code_2011":26260,"b60":null},"id":"lga_vic_crime_statistics_2012_2016.fid--38e292b1_16a853dde5d_-3815"},{"type":"Feature","properties":{"lga_name11":"Stonnington (C)","b40":3574,"lga_code_2011":26350,"b60":null},"id":"lga_vic_crime_statistics_2012_2016.fid--38e292b1_16a853dde5d_-3814"},{"type":"Feature","properties":{"lga_name11":"Strathbogie (S)","b40":139,"lga_code_2011":26430,"b60":null},"id":"lga_vic_crime_statistics_2012_2016.fid--38e292b1_16a853dde5d_-3813"},{"type":"Feature","properties":{"lga_name11":"Surf Coast (S)","b40":389,"lga_code_2011":26490,"b60":null},"id":"lga_vic_crime_statistics_2012_2016.fid--38e292b1_16a853dde5d_-3812"},{"type":"Feature","properties":{"lga_name11":"Swan Hill (RC)","b40":311,"lga_code_2011":26610,"b60":null},"id":"lga_vic_crime_statistics_2012_2016.fid--38e292b1_16a853dde5d_-3811"},{"type":"Feature","properties":{"lga_name11":"Towong (S)","b40":68,"lga_code_2011":26670,"b60":null},"id":"lga_vic_crime_statistics_2012_2016.fid--38e292b1_16a853dde5d_-3810"},{"type":"Feature","properties":{"lga_name11":"Wangaratta (RC)","b40":539,"lga_code_2011":26700,"b60":null},"id":"lga_vic_crime_statistics_2012_2016.fid--38e292b1_16a853dde5d_-380f"},{"type":"Feature","properties":{"lga_name11":"Warrnambool (C)","b40":457,"lga_code_2011":26730,"b60":null},"id":"lga_vic_crime_statistics_2012_2016.fid--38e292b1_16a853dde5d_-380e"},{"type":"Feature","properties":{"lga_name11":"Wellington (S)","b40":1213,"lga_code_2011":26810,"b60":null},"id":"lga_vic_crime_statistics_2012_2016.fid--38e292b1_16a853dde5d_-380d"},{"type":"Feature","properties":{"lga_name11":"West Wimmera (S)","b40":51,"lga_code_2011":26890,"b60":null},"id":"lga_vic_crime_statistics_2012_2016.fid--38e292b1_16a853dde5d_-380c"},{"type":"Feature","properties":{"lga_name11":"Whitehorse (C)","b40":3102,"lga_code_2011":26980,"b60":null},"id":"lga_vic_crime_statistics_2012_2016.fid--38e292b1_16a853dde5d_-380b"},{"type":"Feature","properties":{"lga_name11":"Whittlesea (C)","b40":4491,"lga_code_2011":27070,"b60":null},"id":"lga_vic_crime_statistics_2012_2016.fid--38e292b1_16a853dde5d_-380a"},{"type":"Feature","properties":{"lga_name11":"Wodonga (RC)","b40":892,"lga_code_2011":27170,"b60":2},"id":"lga_vic_crime_statistics_2012_2016.fid--38e292b1_16a853dde5d_-3809"},{"type":"Feature","properties":{"lga_name11":"Wyndham (C)","b40":4768,"lga_code_2011":27260,"b60":null},"id":"lga_vic_crime_statistics_2012_2016.fid--38e292b1_16a853dde5d_-3808"},{"type":"Feature","properties":{"lga_name11":"Yarra (C)","b40":4160,"lga_code_2011":27350,"b60":null},"id":"lga_vic_crime_statistics_2012_2016.fid--38e292b1_16a853dde5d_-3807"},{"type":"Feature","properties":{"lga_name11":"Yarra Ranges (S)","b40":1769,"lga_code_2011":27450,"b60":null},"id":"lga_vic_crime_statistics_2012_2016.fid--38e292b1_16a853dde5d_-3806"},{"type":"Feature","properties":{"lga_name11":"Yarriambiack (S)","b40":57,"lga_code_2011":27630,"b60":null},"id":"lga_vic_crime_statistics_2012_2016.fid--38e292b1_16a853dde5d_-3805"},{"type":"Feature","properties":{"lga_name11":"Alpine (S)","b40":211,"lga_code_2011":20110,"b60":null},"id":"lga_vic_crime_statistics_2012_2016.fid--38e292b1_16a853dde5d_-3804"},{"type":"Feature","properties":{"lga_name11":"Ararat (RC)","b40":178,"lga_code_2011":20260,"b60":null},"id":"lga_vic_crime_statistics_2012_2016.fid--38e292b1_16a853dde5d_-3803"},{"type":"Feature","properties":{"lga_name11":"Ballarat (C)","b40":3029,"lga_code_2011":20570,"b60":null},"id":"lga_vic_crime_statistics_2012_2016.fid--38e292b1_16a853dde5d_-3802"},{"type":"Feature","properties":{"lga_name11":"Banyule (C)","b40":2748,"lga_code_2011":20660,"b60":null},"id":"lga_vic_crime_statistics_2012_2016.fid--38e292b1_16a853dde5d_-3801"},{"type":"Feature","properties":{"lga_name11":"Bass Coast (S)","b40":582,"lga_code_2011":20740,"b60":null},"id":"lga_vic_crime_statistics_2012_2016.fid--38e292b1_16a853dde5d_-3800"},{"type":"Feature","properties":{"lga_name11":"Baw Baw (S)","b40":712,"lga_code_2011":20830,"b60":null},"id":"lga_vic_crime_statistics_2012_2016.fid--38e292b1_16a853dde5d_-37ff"},{"type":"Feature","properties":{"lga_name11":"Bayside (C)","b40":1462,"lga_code_2011":20910,"b60":null},"id":"lga_vic_crime_statistics_2012_2016.fid--38e292b1_16a853dde5d_-37fe"},{"type":"Feature","properties":{"lga_name11":"Benalla (RC)","b40":225,"lga_code_2011":21010,"b60":null},"id":"lga_vic_crime_statistics_2012_2016.fid--38e292b1_16a853dde5d_-37fd"},{"type":"Feature","properties":{"lga_name11":"Boroondara (C)","b40":2713,"lga_code_2011":21110,"b60":null},"id":"lga_vic_crime_statistics_2012_2016.fid--38e292b1_16a853dde5d_-37fc"},{"type":"Feature","properties":{"lga_name11":"Brimbank (C)","b40":5990,"lga_code_2011":21180,"b60":null},"id":"lga_vic_crime_statistics_2012_2016.fid--38e292b1_16a853dde5d_-37fb"},{"type":"Feature","properties":{"lga_name11":"Buloke (S)","b40":55,"lga_code_2011":21270,"b60":null},"id":"lga_vic_crime_statistics_2012_2016.fid--38e292b1_16a853dde5d_-37fa"},{"type":"Feature","properties":{"lga_name11":"Campaspe (S)","b40":969,"lga_code_2011":21370,"b60":null},"id":"lga_vic_crime_statistics_2012_2016.fid--38e292b1_16a853dde5d_-37f9"},{"type":"Feature","properties":{"lga_name11":"Cardinia (S)","b40":1688,"lga_code_2011":21450,"b60":null},"id":"lga_vic_crime_statistics_2012_2016.fid--38e292b1_16a853dde5d_-37f8"},{"type":"Feature","properties":{"lga_name11":"Casey (C)","b40":5528,"lga_code_2011":21610,"b60":null},"id":"lga_vic_crime_statistics_2012_2016.fid--38e292b1_16a853dde5d_-37f7"},{"type":"Feature","properties":{"lga_name11":"Central Goldfields (S)","b40":204,"lga_code_2011":21670,"b60":null},"id":"lga_vic_crime_statistics_2012_2016.fid--38e292b1_16a853dde5d_-37f6"},{"type":"Feature","properties":{"lga_name11":"Colac-Otway (S)","b40":369,"lga_code_2011":21750,"b60":null},"id":"lga_vic_crime_statistics_2012_2016.fid--38e292b1_16a853dde5d_-37f5"},{"type":"Feature","properties":{"lga_name11":"Corangamite (S)","b40":171,"lga_code_2011":21830,"b60":null},"id":"lga_vic_crime_statistics_2012_2016.fid--38e292b1_16a853dde5d_-37f4"},{"type":"Feature","properties":{"lga_name11":"Darebin (C)","b40":5994,"lga_code_2011":21890,"b60":null},"id":"lga_vic_crime_statistics_2012_2016.fid--38e292b1_16a853dde5d_-37f3"},{"type":"Feature","properties":{"lga_name11":"East Gippsland (S)","b40":745,"lga_code_2011":22110,"b60":null},"id":"lga_vic_crime_statistics_2012_2016.fid--38e292b1_16a853dde5d_-37f2"},{"type":"Feature","properties":{"lga_name11":"Frankston (C)","b40":4326,"lga_code_2011":22170,"b60":null},"id":"lga_vic_crime_statistics_2012_2016.fid--38e292b1_16a853dde5d_-37f1"},{"type":"Feature","properties":{"lga_name11":"Gannawarra (S)","b40":138,"lga_code_2011":22250,"b60":null},"id":"lga_vic_crime_statistics_2012_2016.fid--38e292b1_16a853dde5d_-37f0"},{"type":"Feature","properties":{"lga_name11":"Golden Plains (S)","b40":153,"lga_code_2011":22490,"b60":null},"id":"lga_vic_crime_statistics_2012_2016.fid--38e292b1_16a853dde5d_-37ef"},{"type":"Feature","properties":{"lga_name11":"Greater Bendigo (C)","b40":2152,"lga_code_2011":22620,"b60":null},"id":"lga_vic_crime_statistics_2012_2016.fid--38e292b1_16a853dde5d_-37ee"},{"type":"Feature","properties":{"lga_name11":"Greater Dandenong (C)","b40":4456,"lga_code_2011":22670,"b60":null},"id":"lga_vic_crime_statistics_2012_2016.fid--38e292b1_16a853dde5d_-37ed"},{"type":"Feature","properties":{"lga_name11":"Greater Geelong (C)","b40":6248,"lga_code_2011":22750,"b60":null},"id":"lga_vic_crime_statistics_2012_2016.fid--38e292b1_16a853dde5d_-37ec"},{"type":"Feature","properties":{"lga_name11":"Greater Shepparton (C)","b40":1781,"lga_code_2011":22830,"b60":1},"id":"lga_vic_crime_statistics_2012_2016.fid--38e292b1_16a853dde5d_-37eb"},{"type":"Feature","properties":{"lga_name11":"Hepburn (S)","b40":139,"lga_code_2011":22910,"b60":null},"id":"lga_vic_crime_statistics_2012_2016.fid--38e292b1_16a853dde5d_-37ea"},{"type":"Feature","properties":{"lga_name11":"Hindmarsh (S)","b40":35,"lga_code_2011":22980,"b60":null},"id":"lga_vic_crime_statistics_2012_2016.fid--38e292b1_16a853dde5d_-37e9"},{"type":"Feature","properties":{"lga_name11":"Hobsons Bay (C)","b40":2740,"lga_code_2011":23110,"b60":null},"id":"lga_vic_crime_statistics_2012_2016.fid--38e292b1_16a853dde5d_-37e8"},{"type":"Feature","properties":{"lga_name11":"Horsham (RC)","b40":476,"lga_code_2011":23190,"b60":null},"id":"lga_vic_crime_statistics_2012_2016.fid--38e292b1_16a853dde5d_-37e7"},{"type":"Feature","properties":{"lga_name11":"Hume (C)","b40":5855,"lga_code_2011":23270,"b60":null},"id":"lga_vic_crime_statistics_2012_2016.fid--38e292b1_16a853dde5d_-37e6"},{"type":"Feature","properties":{"lga_name11":"Indigo (S)","b40":88,"lga_code_2011":23350,"b60":null},"id":"lga_vic_crime_statistics_2012_2016.fid--38e292b1_16a853dde5d_-37e5"},{"type":"Feature","properties":{"lga_name11":"Kingston (C)","b40":3507,"lga_code_2011":23430,"b60":null},"id":"lga_vic_crime_statistics_2012_2016.fid--38e292b1_16a853dde5d_-37e4"},{"type":"Feature","properties":{"lga_name11":"Knox (C)","b40":3852,"lga_code_2011":23670,"b60":null},"id":"lga_vic_crime_statistics_2012_2016.fid--38e292b1_16a853dde5d_-37e3"},{"type":"Feature","properties":{"lga_name11":"Latrobe (C)","b40":2048,"lga_code_2011":23810,"b60":null},"id":"lga_vic_crime_statistics_2012_2016.fid--38e292b1_16a853dde5d_-37e2"},{"type":"Feature","properties":{"lga_name11":"Loddon (S)","b40":83,"lga_code_2011":23940,"b60":null},"id":"lga_vic_crime_statistics_2012_2016.fid--38e292b1_16a853dde5d_-37e1"},{"type":"Feature","properties":{"lga_name11":"Glen Eira (C)","b40":1900,"lga_code_2011":22310,"b60":null},"id":"lga_vic_crime_statistics_2012_2016.fid--38e292b1_16a853dde5d_-37e0"},{"type":"Feature","properties":{"lga_name11":"Glenelg (S)","b40":445,"lga_code_2011":22410,"b60":null},"id":"lga_vic_crime_statistics_2012_2016.fid--38e292b1_16a853dde5d_-37df"},{"type":"Feature","properties":{"lga_name11":"Macedon Ranges (S)","b40":627,"lga_code_2011":24130,"b60":null},"id":"lga_vic_crime_statistics_2012_2016.fid--38e292b1_16a853dde5d_-37de"},{"type":"Feature","properties":{"lga_name11":"Manningham (C)","b40":1571,"lga_code_2011":24210,"b60":null},"id":"lga_vic_crime_statistics_2012_2016.fid--38e292b1_16a853dde5d_-37dd"},{"type":"Feature","properties":{"lga_name11":"Mansfield (S)","b40":182,"lga_code_2011":24250,"b60":null},"id":"lga_vic_crime_statistics_2012_2016.fid--38e292b1_16a853dde5d_-37dc"},{"type":"Feature","properties":{"lga_name11":"Maribyrnong (C)","b40":3567,"lga_code_2011":24330,"b60":null},"id":"lga_vic_crime_statistics_2012_2016.fid--38e292b1_16a853dde5d_-37db"},{"type":"Feature","properties":{"lga_name11":"Maroondah (C)","b40":2438,"lga_code_2011":24410,"b60":null},"id":"lga_vic_crime_statistics_2012_2016.fid--38e292b1_16a853dde5d_-37da"},{"type":"Feature","properties":{"lga_name11":"Melbourne (C)","b40":10271,"lga_code_2011":24600,"b60":null},"id":"lga_vic_crime_statistics_2012_2016.fid--38e292b1_16a853dde5d_-37d9"},{"type":"Feature","properties":{"lga_name11":"Melton (S)","b40":3561,"lga_code_2011":24650,"b60":1},"id":"lga_vic_crime_statistics_2012_2016.fid--38e292b1_16a853dde5d_-37d8"},{"type":"Feature","properties":{"lga_name11":"Mildura (RC)","b40":1435,"lga_code_2011":24780,"b60":null},"id":"lga_vic_crime_statistics_2012_2016.fid--38e292b1_16a853dde5d_-37d7"},{"type":"Feature","properties":{"lga_name11":"Mitchell (S)","b40":644,"lga_code_2011":24850,"b60":null},"id":"lga_vic_crime_statistics_2012_2016.fid--38e292b1_16a853dde5d_-37d6"},{"type":"Feature","properties":{"lga_name11":"Moira (S)","b40":332,"lga_code_2011":24900,"b60":null},"id":"lga_vic_crime_statistics_2012_2016.fid--38e292b1_16a853dde5d_-37d5"},{"type":"Feature","properties":{"lga_name11":"Monash (C)","b40":3472,"lga_code_2011":24970,"b60":null},"id":"lga_vic_crime_statistics_2012_2016.fid--38e292b1_16a853dde5d_-37d4"},{"type":"Feature","properties":{"lga_name11":"Moonee Valley (C)","b40":3169,"lga_code_2011":25060,"b60":null},"id":"lga_vic_crime_statistics_2012_2016.fid--38e292b1_16a853dde5d_-37d3"},{"type":"Feature","properties":{"lga_name11":"Moorabool (S)","b40":580,"lga_code_2011":25150,"b60":null},"id":"lga_vic_crime_statistics_2012_2016.fid--38e292b1_16a853dde5d_-37d2"},{"type":"Feature","properties":{"lga_name11":"Moreland (C)","b40":5182,"lga_code_2011":25250,"b60":null},"id":"lga_vic_crime_statistics_2012_2016.fid--38e292b1_16a853dde5d_-37d1"},{"type":"Feature","properties":{"lga_name11":"Mornington Peninsula (S)","b40":3141,"lga_code_2011":25340,"b60":null},"id":"lga_vic_crime_statistics_2012_2016.fid--38e292b1_16a853dde5d_-37d0"},{"type":"Feature","properties":{"lga_name11":"Mount Alexander (S)","b40":231,"lga_code_2011":25430,"b60":null},"id":"lga_vic_crime_statistics_2012_2016.fid--38e292b1_16a853dde5d_-37cf"},{"type":"Feature","properties":{"lga_name11":"Moyne (S)","b40":218,"lga_code_2011":25490,"b60":null},"id":"lga_vic_crime_statistics_2012_2016.fid--38e292b1_16a853dde5d_-37ce"},{"type":"Feature","properties":{"lga_name11":"Murrindindi (S)","b40":151,"lga_code_2011":25620,"b60":null},"id":"lga_vic_crime_statistics_2012_2016.fid--38e292b1_16a853dde5d_-37cd"},{"type":"Feature","properties":{"lga_name11":"Nillumbik (S)","b40":704,"lga_code_2011":25710,"b60":null},"id":"lga_vic_crime_statistics_2012_2016.fid--38e292b1_16a853dde5d_-37cc"},{"type":"Feature","properties":{"lga_name11":"Northern Grampians (S)","b40":138,"lga_code_2011":25810,"b60":null},"id":"lga_vic_crime_statistics_2012_2016.fid--38e292b1_16a853dde5d_-37cb"},{"type":"Feature","properties":{"lga_name11":"Port Phillip (C)","b40":4213,"lga_code_2011":25900,"b60":null},"id":"lga_vic_crime_statistics_2012_2016.fid--38e292b1_16a853dde5d_-37ca"},{"type":"Feature","properties":{"lga_name11":"Pyrenees (S)","b40":131,"lga_code_2011":25990,"b60":null},"id":"lga_vic_crime_statistics_2012_2016.fid--38e292b1_16a853dde5d_-37c9"},{"type":"Feature","properties":{"lga_name11":"Queenscliffe (B)","b40":36,"lga_code_2011":26080,"b60":null},"id":"lga_vic_crime_statistics_2012_2016.fid--38e292b1_16a853dde5d_-37c8"},{"type":"Feature","properties":{"lga_name11":"South Gippsland (S)","b40":307,"lga_code_2011":26170,"b60":null},"id":"lga_vic_crime_statistics_2012_2016.fid--38e292b1_16a853dde5d_-37c7"},{"type":"Feature","properties":{"lga_name11":"Southern Grampians (S)","b40":191,"lga_code_2011":26260,"b60":null},"id":"lga_vic_crime_statistics_2012_2016.fid--38e292b1_16a853dde5d_-37c6"},{"type":"Feature","properties":{"lga_name11":"Stonnington (C)","b40":3854,"lga_code_2011":26350,"b60":null},"id":"lga_vic_crime_statistics_2012_2016.fid--38e292b1_16a853dde5d_-37c5"},{"type":"Feature","properties":{"lga_name11":"Strathbogie (S)","b40":146,"lga_code_2011":26430,"b60":2},"id":"lga_vic_crime_statistics_2012_2016.fid--38e292b1_16a853dde5d_-37c4"},{"type":"Feature","properties":{"lga_name11":"Surf Coast (S)","b40":445,"lga_code_2011":26490,"b60":null},"id":"lga_vic_crime_statistics_2012_2016.fid--38e292b1_16a853dde5d_-37c3"},{"type":"Feature","properties":{"lga_name11":"Swan Hill (RC)","b40":424,"lga_code_2011":26610,"b60":null},"id":"lga_vic_crime_statistics_2012_2016.fid--38e292b1_16a853dde5d_-37c2"},{"type":"Feature","properties":{"lga_name11":"Towong (S)","b40":68,"lga_code_2011":26670,"b60":null},"id":"lga_vic_crime_statistics_2012_2016.fid--38e292b1_16a853dde5d_-37c1"},{"type":"Feature","properties":{"lga_name11":"Wangaratta (RC)","b40":458,"lga_code_2011":26700,"b60":null},"id":"lga_vic_crime_statistics_2012_2016.fid--38e292b1_16a853dde5d_-37c0"},{"type":"Feature","properties":{"lga_name11":"Warrnambool (C)","b40":429,"lga_code_2011":26730,"b60":null},"id":"lga_vic_crime_statistics_2012_2016.fid--38e292b1_16a853dde5d_-37bf"},{"type":"Feature","properties":{"lga_name11":"Wellington (S)","b40":973,"lga_code_2011":26810,"b60":null},"id":"lga_vic_crime_statistics_2012_2016.fid--38e292b1_16a853dde5d_-37be"},{"type":"Feature","properties":{"lga_name11":"West Wimmera (S)","b40":36,"lga_code_2011":26890,"b60":null},"id":"lga_vic_crime_statistics_2012_2016.fid--38e292b1_16a853dde5d_-37bd"},{"type":"Feature","properties":{"lga_name11":"Whitehorse (C)","b40":3099,"lga_code_2011":26980,"b60":null},"id":"lga_vic_crime_statistics_2012_2016.fid--38e292b1_16a853dde5d_-37bc"},{"type":"Feature","properties":{"lga_name11":"Whittlesea (C)","b40":5544,"lga_code_2011":27070,"b60":null},"id":"lga_vic_crime_statistics_2012_2016.fid--38e292b1_16a853dde5d_-37bb"},{"type":"Feature","properties":{"lga_name11":"Wodonga (RC)","b40":746,"lga_code_2011":27170,"b60":null},"id":"lga_vic_crime_statistics_2012_2016.fid--38e292b1_16a853dde5d_-37ba"},{"type":"Feature","properties":{"lga_name11":"Wyndham (C)","b40":4987,"lga_code_2011":27260,"b60":1},"id":"lga_vic_crime_statistics_2012_2016.fid--38e292b1_16a853dde5d_-37b9"},{"type":"Feature","properties":{"lga_name11":"Yarra (C)","b40":4890,"lga_code_2011":27350,"b60":null},"id":"lga_vic_crime_statistics_2012_2016.fid--38e292b1_16a853dde5d_-37b8"},{"type":"Feature","properties":{"lga_name11":"Yarra Ranges (S)","b40":2247,"lga_code_2011":27450,"b60":null},"id":"lga_vic_crime_statistics_2012_2016.fid--38e292b1_16a853dde5d_-37b7"},{"type":"Feature","properties":{"lga_name11":"Yarriambiack (S)","b40":45,"lga_code_2011":27630,"b60":null},"id":"lga_vic_crime_statistics_2012_2016.fid--38e292b1_16a853dde5d_-37b6"},{"type":"Feature","properties":{"lga_name11":"Alpine (S)","b40":108,"lga_code_2011":20110,"b60":null},"id":"lga_vic_crime_statistics_2012_2016.fid--38e292b1_16a853dde5d_-37b5"},{"type":"Feature","properties":{"lga_name11":"Ararat (RC)","b40":178,"lga_code_2011":20260,"b60":null},"id":"lga_vic_crime_statistics_2012_2016.fid--38e292b1_16a853dde5d_-37b4"},{"type":"Feature","properties":{"lga_name11":"Ballarat (C)","b40":3694,"lga_code_2011":20570,"b60":null},"id":"lga_vic_crime_statistics_2012_2016.fid--38e292b1_16a853dde5d_-37b3"},{"type":"Feature","properties":{"lga_name11":"Banyule (C)","b40":2860,"lga_code_2011":20660,"b60":null},"id":"lga_vic_crime_statistics_2012_2016.fid--38e292b1_16a853dde5d_-37b2"},{"type":"Feature","properties":{"lga_name11":"Bass Coast (S)","b40":483,"lga_code_2011":20740,"b60":null},"id":"lga_vic_crime_statistics_2012_2016.fid--38e292b1_16a853dde5d_-37b1"},{"type":"Feature","properties":{"lga_name11":"Baw Baw (S)","b40":827,"lga_code_2011":20830,"b60":null},"id":"lga_vic_crime_statistics_2012_2016.fid--38e292b1_16a853dde5d_-37b0"},{"type":"Feature","properties":{"lga_name11":"Bayside (C)","b40":1558,"lga_code_2011":20910,"b60":null},"id":"lga_vic_crime_statistics_2012_2016.fid--38e292b1_16a853dde5d_-37af"},{"type":"Feature","properties":{"lga_name11":"Benalla (RC)","b40":146,"lga_code_2011":21010,"b60":null},"id":"lga_vic_crime_statistics_2012_2016.fid--38e292b1_16a853dde5d_-37ae"},{"type":"Feature","properties":{"lga_name11":"Boroondara (C)","b40":2781,"lga_code_2011":21110,"b60":1},"id":"lga_vic_crime_statistics_2012_2016.fid--38e292b1_16a853dde5d_-37ad"},{"type":"Feature","properties":{"lga_name11":"Brimbank (C)","b40":6632,"lga_code_2011":21180,"b60":null},"id":"lga_vic_crime_statistics_2012_2016.fid--38e292b1_16a853dde5d_-37ac"},{"type":"Feature","properties":{"lga_name11":"Buloke (S)","b40":77,"lga_code_2011":21270,"b60":null},"id":"lga_vic_crime_statistics_2012_2016.fid--38e292b1_16a853dde5d_-37ab"},{"type":"Feature","properties":{"lga_name11":"Campaspe (S)","b40":867,"lga_code_2011":21370,"b60":null},"id":"lga_vic_crime_statistics_2012_2016.fid--38e292b1_16a853dde5d_-37aa"},{"type":"Feature","properties":{"lga_name11":"Cardinia (S)","b40":2117,"lga_code_2011":21450,"b60":1},"id":"lga_vic_crime_statistics_2012_2016.fid--38e292b1_16a853dde5d_-37a9"},{"type":"Feature","properties":{"lga_name11":"Casey (C)","b40":6665,"lga_code_2011":21610,"b60":null},"id":"lga_vic_crime_statistics_2012_2016.fid--38e292b1_16a853dde5d_-37a8"},{"type":"Feature","properties":{"lga_name11":"Central Goldfields (S)","b40":229,"lga_code_2011":21670,"b60":null},"id":"lga_vic_crime_statistics_2012_2016.fid--38e292b1_16a853dde5d_-37a7"},{"type":"Feature","properties":{"lga_name11":"Colac-Otway (S)","b40":347,"lga_code_2011":21750,"b60":null},"id":"lga_vic_crime_statistics_2012_2016.fid--38e292b1_16a853dde5d_-37a6"},{"type":"Feature","properties":{"lga_name11":"Corangamite (S)","b40":153,"lga_code_2011":21830,"b60":null},"id":"lga_vic_crime_statistics_2012_2016.fid--38e292b1_16a853dde5d_-37a5"},{"type":"Feature","properties":{"lga_name11":"Darebin (C)","b40":6548,"lga_code_2011":21890,"b60":1},"id":"lga_vic_crime_statistics_2012_2016.fid--38e292b1_16a853dde5d_-37a4"},{"type":"Feature","properties":{"lga_name11":"East Gippsland (S)","b40":874,"lga_code_2011":22110,"b60":null},"id":"lga_vic_crime_statistics_2012_2016.fid--38e292b1_16a853dde5d_-37a3"},{"type":"Feature","properties":{"lga_name11":"Frankston (C)","b40":4391,"lga_code_2011":22170,"b60":null},"id":"lga_vic_crime_statistics_2012_2016.fid--38e292b1_16a853dde5d_-37a2"},{"type":"Feature","properties":{"lga_name11":"Gannawarra (S)","b40":103,"lga_code_2011":22250,"b60":null},"id":"lga_vic_crime_statistics_2012_2016.fid--38e292b1_16a853dde5d_-37a1"},{"type":"Feature","properties":{"lga_name11":"Golden Plains (S)","b40":209,"lga_code_2011":22490,"b60":null},"id":"lga_vic_crime_statistics_2012_2016.fid--38e292b1_16a853dde5d_-37a0"},{"type":"Feature","properties":{"lga_name11":"Greater Bendigo (C)","b40":2184,"lga_code_2011":22620,"b60":12},"id":"lga_vic_crime_statistics_2012_2016.fid--38e292b1_16a853dde5d_-379f"},{"type":"Feature","properties":{"lga_name11":"Greater Dandenong (C)","b40":5860,"lga_code_2011":22670,"b60":null},"id":"lga_vic_crime_statistics_2012_2016.fid--38e292b1_16a853dde5d_-379e"},{"type":"Feature","properties":{"lga_name11":"Greater Geelong (C)","b40":7226,"lga_code_2011":22750,"b60":9},"id":"lga_vic_crime_statistics_2012_2016.fid--38e292b1_16a853dde5d_-379d"},{"type":"Feature","properties":{"lga_name11":"Greater Shepparton (C)","b40":1964,"lga_code_2011":22830,"b60":null},"id":"lga_vic_crime_statistics_2012_2016.fid--38e292b1_16a853dde5d_-379c"},{"type":"Feature","properties":{"lga_name11":"Hepburn (S)","b40":253,"lga_code_2011":22910,"b60":null},"id":"lga_vic_crime_statistics_2012_2016.fid--38e292b1_16a853dde5d_-379b"},{"type":"Feature","properties":{"lga_name11":"Hindmarsh (S)","b40":35,"lga_code_2011":22980,"b60":null},"id":"lga_vic_crime_statistics_2012_2016.fid--38e292b1_16a853dde5d_-379a"},{"type":"Feature","properties":{"lga_name11":"Hobsons Bay (C)","b40":2595,"lga_code_2011":23110,"b60":null},"id":"lga_vic_crime_statistics_2012_2016.fid--38e292b1_16a853dde5d_-3799"},{"type":"Feature","properties":{"lga_name11":"Horsham (RC)","b40":585,"lga_code_2011":23190,"b60":null},"id":"lga_vic_crime_statistics_2012_2016.fid--38e292b1_16a853dde5d_-3798"},{"type":"Feature","properties":{"lga_name11":"Hume (C)","b40":6211,"lga_code_2011":23270,"b60":1},"id":"lga_vic_crime_statistics_2012_2016.fid--38e292b1_16a853dde5d_-3797"},{"type":"Feature","properties":{"lga_name11":"Indigo (S)","b40":121,"lga_code_2011":23350,"b60":null},"id":"lga_vic_crime_statistics_2012_2016.fid--38e292b1_16a853dde5d_-3796"},{"type":"Feature","properties":{"lga_name11":"Kingston (C)","b40":3630,"lga_code_2011":23430,"b60":null},"id":"lga_vic_crime_statistics_2012_2016.fid--38e292b1_16a853dde5d_-3795"},{"type":"Feature","properties":{"lga_name11":"Knox (C)","b40":3586,"lga_code_2011":23670,"b60":null},"id":"lga_vic_crime_statistics_2012_2016.fid--38e292b1_16a853dde5d_-3794"},{"type":"Feature","properties":{"lga_name11":"Latrobe (C)","b40":2556,"lga_code_2011":23810,"b60":1},"id":"lga_vic_crime_statistics_2012_2016.fid--38e292b1_16a853dde5d_-3793"},{"type":"Feature","properties":{"lga_name11":"Glen Eira (C)","b40":2204,"lga_code_2011":22310,"b60":null},"id":"lga_vic_crime_statistics_2012_2016.fid--38e292b1_16a853dde5d_-3792"},{"type":"Feature","properties":{"lga_name11":"Glenelg (S)","b40":362,"lga_code_2011":22410,"b60":null},"id":"lga_vic_crime_statistics_2012_2016.fid--38e292b1_16a853dde5d_-3791"},{"type":"Feature","properties":{"lga_name11":"Loddon (S)","b40":89,"lga_code_2011":23940,"b60":null},"id":"lga_vic_crime_statistics_2012_2016.fid--38e292b1_16a853dde5d_-3790"},{"type":"Feature","properties":{"lga_name11":"Macedon Ranges (S)","b40":535,"lga_code_2011":24130,"b60":null},"id":"lga_vic_crime_statistics_2012_2016.fid--38e292b1_16a853dde5d_-378f"},{"type":"Feature","properties":{"lga_name11":"Manningham (C)","b40":1510,"lga_code_2011":24210,"b60":2},"id":"lga_vic_crime_statistics_2012_2016.fid--38e292b1_16a853dde5d_-378e"},{"type":"Feature","properties":{"lga_name11":"Mansfield (S)","b40":136,"lga_code_2011":24250,"b60":null},"id":"lga_vic_crime_statistics_2012_2016.fid--38e292b1_16a853dde5d_-378d"},{"type":"Feature","properties":{"lga_name11":"Maribyrnong (C)","b40":3545,"lga_code_2011":24330,"b60":null},"id":"lga_vic_crime_statistics_2012_2016.fid--38e292b1_16a853dde5d_-378c"},{"type":"Feature","properties":{"lga_name11":"Maroondah (C)","b40":2546,"lga_code_2011":24410,"b60":3},"id":"lga_vic_crime_statistics_2012_2016.fid--38e292b1_16a853dde5d_-378b"},{"type":"Feature","properties":{"lga_name11":"Melbourne (C)","b40":10988,"lga_code_2011":24600,"b60":2},"id":"lga_vic_crime_statistics_2012_2016.fid--38e292b1_16a853dde5d_-378a"},{"type":"Feature","properties":{"lga_name11":"Melton (S)","b40":3920,"lga_code_2011":24650,"b60":8},"id":"lga_vic_crime_statistics_2012_2016.fid--38e292b1_16a853dde5d_-3789"},{"type":"Feature","properties":{"lga_name11":"Mildura (RC)","b40":1472,"lga_code_2011":24780,"b60":null},"id":"lga_vic_crime_statistics_2012_2016.fid--38e292b1_16a853dde5d_-3788"},{"type":"Feature","properties":{"lga_name11":"Mitchell (S)","b40":857,"lga_code_2011":24850,"b60":null},"id":"lga_vic_crime_statistics_2012_2016.fid--38e292b1_16a853dde5d_-3787"},{"type":"Feature","properties":{"lga_name11":"Moira (S)","b40":303,"lga_code_2011":24900,"b60":null},"id":"lga_vic_crime_statistics_2012_2016.fid--38e292b1_16a853dde5d_-3786"},{"type":"Feature","properties":{"lga_name11":"Monash (C)","b40":3808,"lga_code_2011":24970,"b60":null},"id":"lga_vic_crime_statistics_2012_2016.fid--38e292b1_16a853dde5d_-3785"},{"type":"Feature","properties":{"lga_name11":"Moonee Valley (C)","b40":3670,"lga_code_2011":25060,"b60":null},"id":"lga_vic_crime_statistics_2012_2016.fid--38e292b1_16a853dde5d_-3784"},{"type":"Feature","properties":{"lga_name11":"Moorabool (S)","b40":704,"lga_code_2011":25150,"b60":1},"id":"lga_vic_crime_statistics_2012_2016.fid--38e292b1_16a853dde5d_-3783"},{"type":"Feature","properties":{"lga_name11":"Moreland (C)","b40":5615,"lga_code_2011":25250,"b60":null},"id":"lga_vic_crime_statistics_2012_2016.fid--38e292b1_16a853dde5d_-3782"},{"type":"Feature","properties":{"lga_name11":"Mornington Peninsula (S)","b40":2895,"lga_code_2011":25340,"b60":null},"id":"lga_vic_crime_statistics_2012_2016.fid--38e292b1_16a853dde5d_-3781"},{"type":"Feature","properties":{"lga_name11":"Mount Alexander (S)","b40":205,"lga_code_2011":25430,"b60":null},"id":"lga_vic_crime_statistics_2012_2016.fid--38e292b1_16a853dde5d_-3780"},{"type":"Feature","properties":{"lga_name11":"Moyne (S)","b40":143,"lga_code_2011":25490,"b60":null},"id":"lga_vic_crime_statistics_2012_2016.fid--38e292b1_16a853dde5d_-377f"},{"type":"Feature","properties":{"lga_name11":"Murrindindi (S)","b40":171,"lga_code_2011":25620,"b60":null},"id":"lga_vic_crime_statistics_2012_2016.fid--38e292b1_16a853dde5d_-377e"},{"type":"Feature","properties":{"lga_name11":"Nillumbik (S)","b40":835,"lga_code_2011":25710,"b60":null},"id":"lga_vic_crime_statistics_2012_2016.fid--38e292b1_16a853dde5d_-377d"},{"type":"Feature","properties":{"lga_name11":"Northern Grampians (S)","b40":167,"lga_code_2011":25810,"b60":null},"id":"lga_vic_crime_statistics_2012_2016.fid--38e292b1_16a853dde5d_-377c"},{"type":"Feature","properties":{"lga_name11":"Port Phillip (C)","b40":4665,"lga_code_2011":25900,"b60":null},"id":"lga_vic_crime_statistics_2012_2016.fid--38e292b1_16a853dde5d_-377b"},{"type":"Feature","properties":{"lga_name11":"Pyrenees (S)","b40":107,"lga_code_2011":25990,"b60":null},"id":"lga_vic_crime_statistics_2012_2016.fid--38e292b1_16a853dde5d_-377a"},{"type":"Feature","properties":{"lga_name11":"Queenscliffe (B)","b40":46,"lga_code_2011":26080,"b60":null},"id":"lga_vic_crime_statistics_2012_2016.fid--38e292b1_16a853dde5d_-3779"},{"type":"Feature","properties":{"lga_name11":"South Gippsland (S)","b40":299,"lga_code_2011":26170,"b60":null},"id":"lga_vic_crime_statistics_2012_2016.fid--38e292b1_16a853dde5d_-3778"},{"type":"Feature","properties":{"lga_name11":"Southern Grampians (S)","b40":244,"lga_code_2011":26260,"b60":null},"id":"lga_vic_crime_statistics_2012_2016.fid--38e292b1_16a853dde5d_-3777"},{"type":"Feature","properties":{"lga_name11":"Stonnington (C)","b40":4063,"lga_code_2011":26350,"b60":null},"id":"lga_vic_crime_statistics_2012_2016.fid--38e292b1_16a853dde5d_-3776"},{"type":"Feature","properties":{"lga_name11":"Strathbogie (S)","b40":108,"lga_code_2011":26430,"b60":null},"id":"lga_vic_crime_statistics_2012_2016.fid--38e292b1_16a853dde5d_-3775"},{"type":"Feature","properties":{"lga_name11":"Surf Coast (S)","b40":434,"lga_code_2011":26490,"b60":null},"id":"lga_vic_crime_statistics_2012_2016.fid--38e292b1_16a853dde5d_-3774"},{"type":"Feature","properties":{"lga_name11":"Swan Hill (RC)","b40":376,"lga_code_2011":26610,"b60":null},"id":"lga_vic_crime_statistics_2012_2016.fid--38e292b1_16a853dde5d_-3773"},{"type":"Feature","properties":{"lga_name11":"Towong (S)","b40":50,"lga_code_2011":26670,"b60":null},"id":"lga_vic_crime_statistics_2012_2016.fid--38e292b1_16a853dde5d_-3772"},{"type":"Feature","properties":{"lga_name11":"Wangaratta (RC)","b40":441,"lga_code_2011":26700,"b60":null},"id":"lga_vic_crime_statistics_2012_2016.fid--38e292b1_16a853dde5d_-3771"},{"type":"Feature","properties":{"lga_name11":"Warrnambool (C)","b40":510,"lga_code_2011":26730,"b60":null},"id":"lga_vic_crime_statistics_2012_2016.fid--38e292b1_16a853dde5d_-3770"},{"type":"Feature","properties":{"lga_name11":"Wellington (S)","b40":793,"lga_code_2011":26810,"b60":null},"id":"lga_vic_crime_statistics_2012_2016.fid--38e292b1_16a853dde5d_-376f"},{"type":"Feature","properties":{"lga_name11":"West Wimmera (S)","b40":22,"lga_code_2011":26890,"b60":null},"id":"lga_vic_crime_statistics_2012_2016.fid--38e292b1_16a853dde5d_-376e"},{"type":"Feature","properties":{"lga_name11":"Whitehorse (C)","b40":2764,"lga_code_2011":26980,"b60":null},"id":"lga_vic_crime_statistics_2012_2016.fid--38e292b1_16a853dde5d_-376d"},{"type":"Feature","properties":{"lga_name11":"Whittlesea (C)","b40":4967,"lga_code_2011":27070,"b60":3},"id":"lga_vic_crime_statistics_2012_2016.fid--38e292b1_16a853dde5d_-376c"},{"type":"Feature","properties":{"lga_name11":"Wodonga (RC)","b40":818,"lga_code_2011":27170,"b60":null},"id":"lga_vic_crime_statistics_2012_2016.fid--38e292b1_16a853dde5d_-376b"},{"type":"Feature","properties":{"lga_name11":"Wyndham (C)","b40":5321,"lga_code_2011":27260,"b60":1},"id":"lga_vic_crime_statistics_2012_2016.fid--38e292b1_16a853dde5d_-376a"},{"type":"Feature","properties":{"lga_name11":"Yarra (C)","b40":5046,"lga_code_2011":27350,"b60":null},"id":"lga_vic_crime_statistics_2012_2016.fid--38e292b1_16a853dde5d_-3769"},{"type":"Feature","properties":{"lga_name11":"Yarra Ranges (S)","b40":2096,"lga_code_2011":27450,"b60":null},"id":"lga_vic_crime_statistics_2012_2016.fid--38e292b1_16a853dde5d_-3768"},{"type":"Feature","properties":{"lga_name11":"Yarriambiack (S)","b40":76,"lga_code_2011":27630,"b60":null},"id":"lga_vic_crime_statistics_2012_2016.fid--38e292b1_16a853dde5d_-3767"},{"type":"Feature","properties":{"lga_name11":"Alpine (S)","b40":97,"lga_code_2011":20110,"b60":null},"id":"lga_vic_crime_statistics_2012_2016.fid--38e292b1_16a853dde5d_-3766"},{"type":"Feature","properties":{"lga_name11":"Ararat (RC)","b40":184,"lga_code_2011":20260,"b60":null},"id":"lga_vic_crime_statistics_2012_2016.fid--38e292b1_16a853dde5d_-3765"},{"type":"Feature","properties":{"lga_name11":"Ballarat (C)","b40":4163,"lga_code_2011":20570,"b60":null},"id":"lga_vic_crime_statistics_2012_2016.fid--38e292b1_16a853dde5d_-3764"},{"type":"Feature","properties":{"lga_name11":"Banyule (C)","b40":3422,"lga_code_2011":20660,"b60":null},"id":"lga_vic_crime_statistics_2012_2016.fid--38e292b1_16a853dde5d_-3763"},{"type":"Feature","properties":{"lga_name11":"Bass Coast (S)","b40":701,"lga_code_2011":20740,"b60":null},"id":"lga_vic_crime_statistics_2012_2016.fid--38e292b1_16a853dde5d_-3762"},{"type":"Feature","properties":{"lga_name11":"Baw Baw (S)","b40":1052,"lga_code_2011":20830,"b60":null},"id":"lga_vic_crime_statistics_2012_2016.fid--38e292b1_16a853dde5d_-3761"},{"type":"Feature","properties":{"lga_name11":"Bayside (C)","b40":2193,"lga_code_2011":20910,"b60":null},"id":"lga_vic_crime_statistics_2012_2016.fid--38e292b1_16a853dde5d_-3760"},{"type":"Feature","properties":{"lga_name11":"Benalla (RC)","b40":262,"lga_code_2011":21010,"b60":null},"id":"lga_vic_crime_statistics_2012_2016.fid--38e292b1_16a853dde5d_-375f"},{"type":"Feature","properties":{"lga_name11":"Boroondara (C)","b40":3835,"lga_code_2011":21110,"b60":null},"id":"lga_vic_crime_statistics_2012_2016.fid--38e292b1_16a853dde5d_-375e"},{"type":"Feature","properties":{"lga_name11":"Brimbank (C)","b40":6978,"lga_code_2011":21180,"b60":null},"id":"lga_vic_crime_statistics_2012_2016.fid--38e292b1_16a853dde5d_-375d"},{"type":"Feature","properties":{"lga_name11":"Buloke (S)","b40":61,"lga_code_2011":21270,"b60":null},"id":"lga_vic_crime_statistics_2012_2016.fid--38e292b1_16a853dde5d_-375c"},{"type":"Feature","properties":{"lga_name11":"Campaspe (S)","b40":936,"lga_code_2011":21370,"b60":null},"id":"lga_vic_crime_statistics_2012_2016.fid--38e292b1_16a853dde5d_-375b"},{"type":"Feature","properties":{"lga_name11":"Cardinia (S)","b40":2200,"lga_code_2011":21450,"b60":null},"id":"lga_vic_crime_statistics_2012_2016.fid--38e292b1_16a853dde5d_-375a"},{"type":"Feature","properties":{"lga_name11":"Casey (C)","b40":7962,"lga_code_2011":21610,"b60":null},"id":"lga_vic_crime_statistics_2012_2016.fid--38e292b1_16a853dde5d_-3759"},{"type":"Feature","properties":{"lga_name11":"Central Goldfields (S)","b40":334,"lga_code_2011":21670,"b60":null},"id":"lga_vic_crime_statistics_2012_2016.fid--38e292b1_16a853dde5d_-3758"},{"type":"Feature","properties":{"lga_name11":"Colac-Otway (S)","b40":496,"lga_code_2011":21750,"b60":null},"id":"lga_vic_crime_statistics_2012_2016.fid--38e292b1_16a853dde5d_-3757"},{"type":"Feature","properties":{"lga_name11":"Corangamite (S)","b40":237,"lga_code_2011":21830,"b60":null},"id":"lga_vic_crime_statistics_2012_2016.fid--38e292b1_16a853dde5d_-3756"},{"type":"Feature","properties":{"lga_name11":"Darebin (C)","b40":7349,"lga_code_2011":21890,"b60":null},"id":"lga_vic_crime_statistics_2012_2016.fid--38e292b1_16a853dde5d_-3755"},{"type":"Feature","properties":{"lga_name11":"East Gippsland (S)","b40":991,"lga_code_2011":22110,"b60":null},"id":"lga_vic_crime_statistics_2012_2016.fid--38e292b1_16a853dde5d_-3754"},{"type":"Feature","properties":{"lga_name11":"Frankston (C)","b40":4802,"lga_code_2011":22170,"b60":null},"id":"lga_vic_crime_statistics_2012_2016.fid--38e292b1_16a853dde5d_-3753"},{"type":"Feature","properties":{"lga_name11":"Gannawarra (S)","b40":107,"lga_code_2011":22250,"b60":null},"id":"lga_vic_crime_statistics_2012_2016.fid--38e292b1_16a853dde5d_-3752"},{"type":"Feature","properties":{"lga_name11":"Golden Plains (S)","b40":249,"lga_code_2011":22490,"b60":null},"id":"lga_vic_crime_statistics_2012_2016.fid--38e292b1_16a853dde5d_-3751"},{"type":"Feature","properties":{"lga_name11":"Greater Bendigo (C)","b40":2933,"lga_code_2011":22620,"b60":null},"id":"lga_vic_crime_statistics_2012_2016.fid--38e292b1_16a853dde5d_-3750"},{"type":"Feature","properties":{"lga_name11":"Greater Dandenong (C)","b40":6489,"lga_code_2011":22670,"b60":null},"id":"lga_vic_crime_statistics_2012_2016.fid--38e292b1_16a853dde5d_-374f"},{"type":"Feature","properties":{"lga_name11":"Greater Geelong (C)","b40":9200,"lga_code_2011":22750,"b60":null},"id":"lga_vic_crime_statistics_2012_2016.fid--38e292b1_16a853dde5d_-374e"},{"type":"Feature","properties":{"lga_name11":"Greater Shepparton (C)","b40":2038,"lga_code_2011":22830,"b60":null},"id":"lga_vic_crime_statistics_2012_2016.fid--38e292b1_16a853dde5d_-374d"},{"type":"Feature","properties":{"lga_name11":"Hepburn (S)","b40":290,"lga_code_2011":22910,"b60":null},"id":"lga_vic_crime_statistics_2012_2016.fid--38e292b1_16a853dde5d_-374c"},{"type":"Feature","properties":{"lga_name11":"Hindmarsh (S)","b40":83,"lga_code_2011":22980,"b60":null},"id":"lga_vic_crime_statistics_2012_2016.fid--38e292b1_16a853dde5d_-374b"},{"type":"Feature","properties":{"lga_name11":"Hobsons Bay (C)","b40":2603,"lga_code_2011":23110,"b60":null},"id":"lga_vic_crime_statistics_2012_2016.fid--38e292b1_16a853dde5d_-374a"},{"type":"Feature","properties":{"lga_name11":"Horsham (RC)","b40":448,"lga_code_2011":23190,"b60":null},"id":"lga_vic_crime_statistics_2012_2016.fid--38e292b1_16a853dde5d_-3749"},{"type":"Feature","properties":{"lga_name11":"Hume (C)","b40":7955,"lga_code_2011":23270,"b60":null},"id":"lga_vic_crime_statistics_2012_2016.fid--38e292b1_16a853dde5d_-3748"},{"type":"Feature","properties":{"lga_name11":"Indigo (S)","b40":83,"lga_code_2011":23350,"b60":null},"id":"lga_vic_crime_statistics_2012_2016.fid--38e292b1_16a853dde5d_-3747"},{"type":"Feature","properties":{"lga_name11":"Kingston (C)","b40":4184,"lga_code_2011":23430,"b60":null},"id":"lga_vic_crime_statistics_2012_2016.fid--38e292b1_16a853dde5d_-3746"},{"type":"Feature","properties":{"lga_name11":"Knox (C)","b40":4348,"lga_code_2011":23670,"b60":null},"id":"lga_vic_crime_statistics_2012_2016.fid--38e292b1_16a853dde5d_-3745"},{"type":"Feature","properties":{"lga_name11":"Glen Eira (C)","b40":2546,"lga_code_2011":22310,"b60":1},"id":"lga_vic_crime_statistics_2012_2016.fid--38e292b1_16a853dde5d_-3744"},{"type":"Feature","properties":{"lga_name11":"Glenelg (S)","b40":433,"lga_code_2011":22410,"b60":null},"id":"lga_vic_crime_statistics_2012_2016.fid--38e292b1_16a853dde5d_-3743"},{"type":"Feature","properties":{"lga_name11":"Latrobe (C)","b40":3208,"lga_code_2011":23810,"b60":null},"id":"lga_vic_crime_statistics_2012_2016.fid--38e292b1_16a853dde5d_-3742"},{"type":"Feature","properties":{"lga_name11":"Loddon (S)","b40":116,"lga_code_2011":23940,"b60":null},"id":"lga_vic_crime_statistics_2012_2016.fid--38e292b1_16a853dde5d_-3741"},{"type":"Feature","properties":{"lga_name11":"Macedon Ranges (S)","b40":566,"lga_code_2011":24130,"b60":null},"id":"lga_vic_crime_statistics_2012_2016.fid--38e292b1_16a853dde5d_-3740"},{"type":"Feature","properties":{"lga_name11":"Manningham (C)","b40":1762,"lga_code_2011":24210,"b60":null},"id":"lga_vic_crime_statistics_2012_2016.fid--38e292b1_16a853dde5d_-373f"},{"type":"Feature","properties":{"lga_name11":"Mansfield (S)","b40":197,"lga_code_2011":24250,"b60":null},"id":"lga_vic_crime_statistics_2012_2016.fid--38e292b1_16a853dde5d_-373e"},{"type":"Feature","properties":{"lga_name11":"Maribyrnong (C)","b40":4123,"lga_code_2011":24330,"b60":null},"id":"lga_vic_crime_statistics_2012_2016.fid--38e292b1_16a853dde5d_-373d"},{"type":"Feature","properties":{"lga_name11":"Maroondah (C)","b40":2762,"lga_code_2011":24410,"b60":null},"id":"lga_vic_crime_statistics_2012_2016.fid--38e292b1_16a853dde5d_-373c"},{"type":"Feature","properties":{"lga_name11":"Melbourne (C)","b40":12703,"lga_code_2011":24600,"b60":1},"id":"lga_vic_crime_statistics_2012_2016.fid--38e292b1_16a853dde5d_-373b"},{"type":"Feature","properties":{"lga_name11":"Melton (S)","b40":4514,"lga_code_2011":24650,"b60":18},"id":"lga_vic_crime_statistics_2012_2016.fid--38e292b1_16a853dde5d_-373a"},{"type":"Feature","properties":{"lga_name11":"Mildura (RC)","b40":1595,"lga_code_2011":24780,"b60":null},"id":"lga_vic_crime_statistics_2012_2016.fid--38e292b1_16a853dde5d_-3739"},{"type":"Feature","properties":{"lga_name11":"Mitchell (S)","b40":1006,"lga_code_2011":24850,"b60":null},"id":"lga_vic_crime_statistics_2012_2016.fid--38e292b1_16a853dde5d_-3738"},{"type":"Feature","properties":{"lga_name11":"Moira (S)","b40":385,"lga_code_2011":24900,"b60":null},"id":"lga_vic_crime_statistics_2012_2016.fid--38e292b1_16a853dde5d_-3737"},{"type":"Feature","properties":{"lga_name11":"Monash (C)","b40":4433,"lga_code_2011":24970,"b60":null},"id":"lga_vic_crime_statistics_2012_2016.fid--38e292b1_16a853dde5d_-3736"},{"type":"Feature","properties":{"lga_name11":"Moonee Valley (C)","b40":4334,"lga_code_2011":25060,"b60":null},"id":"lga_vic_crime_statistics_2012_2016.fid--38e292b1_16a853dde5d_-3735"},{"type":"Feature","properties":{"lga_name11":"Moorabool (S)","b40":778,"lga_code_2011":25150,"b60":null},"id":"lga_vic_crime_statistics_2012_2016.fid--38e292b1_16a853dde5d_-3734"},{"type":"Feature","properties":{"lga_name11":"Moreland (C)","b40":6466,"lga_code_2011":25250,"b60":null},"id":"lga_vic_crime_statistics_2012_2016.fid--38e292b1_16a853dde5d_-3733"},{"type":"Feature","properties":{"lga_name11":"Mornington Peninsula (S)","b40":3211,"lga_code_2011":25340,"b60":1},"id":"lga_vic_crime_statistics_2012_2016.fid--38e292b1_16a853dde5d_-3732"},{"type":"Feature","properties":{"lga_name11":"Mount Alexander (S)","b40":341,"lga_code_2011":25430,"b60":null},"id":"lga_vic_crime_statistics_2012_2016.fid--38e292b1_16a853dde5d_-3731"},{"type":"Feature","properties":{"lga_name11":"Moyne (S)","b40":179,"lga_code_2011":25490,"b60":null},"id":"lga_vic_crime_statistics_2012_2016.fid--38e292b1_16a853dde5d_-3730"},{"type":"Feature","properties":{"lga_name11":"Murrindindi (S)","b40":171,"lga_code_2011":25620,"b60":null},"id":"lga_vic_crime_statistics_2012_2016.fid--38e292b1_16a853dde5d_-372f"},{"type":"Feature","properties":{"lga_name11":"Nillumbik (S)","b40":1143,"lga_code_2011":25710,"b60":null},"id":"lga_vic_crime_statistics_2012_2016.fid--38e292b1_16a853dde5d_-372e"},{"type":"Feature","properties":{"lga_name11":"Northern Grampians (S)","b40":174,"lga_code_2011":25810,"b60":null},"id":"lga_vic_crime_statistics_2012_2016.fid--38e292b1_16a853dde5d_-372d"},{"type":"Feature","properties":{"lga_name11":"Port Phillip (C)","b40":5505,"lga_code_2011":25900,"b60":null},"id":"lga_vic_crime_statistics_2012_2016.fid--38e292b1_16a853dde5d_-372c"},{"type":"Feature","properties":{"lga_name11":"Pyrenees (S)","b40":130,"lga_code_2011":25990,"b60":null},"id":"lga_vic_crime_statistics_2012_2016.fid--38e292b1_16a853dde5d_-372b"},{"type":"Feature","properties":{"lga_name11":"Queenscliffe (B)","b40":60,"lga_code_2011":26080,"b60":null},"id":"lga_vic_crime_statistics_2012_2016.fid--38e292b1_16a853dde5d_-372a"},{"type":"Feature","properties":{"lga_name11":"South Gippsland (S)","b40":331,"lga_code_2011":26170,"b60":null},"id":"lga_vic_crime_statistics_2012_2016.fid--38e292b1_16a853dde5d_-3729"},{"type":"Feature","properties":{"lga_name11":"Southern Grampians (S)","b40":266,"lga_code_2011":26260,"b60":null},"id":"lga_vic_crime_statistics_2012_2016.fid--38e292b1_16a853dde5d_-3728"},{"type":"Feature","properties":{"lga_name11":"Stonnington (C)","b40":5141,"lga_code_2011":26350,"b60":null},"id":"lga_vic_crime_statistics_2012_2016.fid--38e292b1_16a853dde5d_-3727"},{"type":"Feature","properties":{"lga_name11":"Strathbogie (S)","b40":194,"lga_code_2011":26430,"b60":null},"id":"lga_vic_crime_statistics_2012_2016.fid--38e292b1_16a853dde5d_-3726"},{"type":"Feature","properties":{"lga_name11":"Surf Coast (S)","b40":578,"lga_code_2011":26490,"b60":null},"id":"lga_vic_crime_statistics_2012_2016.fid--38e292b1_16a853dde5d_-3725"},{"type":"Feature","properties":{"lga_name11":"Swan Hill (RC)","b40":422,"lga_code_2011":26610,"b60":null},"id":"lga_vic_crime_statistics_2012_2016.fid--38e292b1_16a853dde5d_-3724"},{"type":"Feature","properties":{"lga_name11":"Towong (S)","b40":59,"lga_code_2011":26670,"b60":null},"id":"lga_vic_crime_statistics_2012_2016.fid--38e292b1_16a853dde5d_-3723"},{"type":"Feature","properties":{"lga_name11":"Wangaratta (RC)","b40":515,"lga_code_2011":26700,"b60":null},"id":"lga_vic_crime_statistics_2012_2016.fid--38e292b1_16a853dde5d_-3722"},{"type":"Feature","properties":{"lga_name11":"Warrnambool (C)","b40":596,"lga_code_2011":26730,"b60":null},"id":"lga_vic_crime_statistics_2012_2016.fid--38e292b1_16a853dde5d_-3721"},{"type":"Feature","properties":{"lga_name11":"Wellington (S)","b40":886,"lga_code_2011":26810,"b60":1},"id":"lga_vic_crime_statistics_2012_2016.fid--38e292b1_16a853dde5d_-3720"},{"type":"Feature","properties":{"lga_name11":"West Wimmera (S)","b40":27,"lga_code_2011":26890,"b60":null},"id":"lga_vic_crime_statistics_2012_2016.fid--38e292b1_16a853dde5d_-371f"},{"type":"Feature","properties":{"lga_name11":"Whitehorse (C)","b40":3002,"lga_code_2011":26980,"b60":null},"id":"lga_vic_crime_statistics_2012_2016.fid--38e292b1_16a853dde5d_-371e"},{"type":"Feature","properties":{"lga_name11":"Whittlesea (C)","b40":6478,"lga_code_2011":27070,"b60":null},"id":"lga_vic_crime_statistics_2012_2016.fid--38e292b1_16a853dde5d_-371d"},{"type":"Feature","properties":{"lga_name11":"Wodonga (RC)","b40":850,"lga_code_2011":27170,"b60":null},"id":"lga_vic_crime_statistics_2012_2016.fid--38e292b1_16a853dde5d_-371c"},{"type":"Feature","properties":{"lga_name11":"Wyndham (C)","b40":6057,"lga_code_2011":27260,"b60":null},"id":"lga_vic_crime_statistics_2012_2016.fid--38e292b1_16a853dde5d_-371b"},{"type":"Feature","properties":{"lga_name11":"Yarra (C)","b40":5983,"lga_code_2011":27350,"b60":null},"id":"lga_vic_crime_statistics_2012_2016.fid--38e292b1_16a853dde5d_-371a"},{"type":"Feature","properties":{"lga_name11":"Yarra Ranges (S)","b40":2602,"lga_code_2011":27450,"b60":null},"id":"lga_vic_crime_statistics_2012_2016.fid--38e292b1_16a853dde5d_-3719"},{"type":"Feature","properties":{"lga_name11":"Yarriambiack (S)","b40":83,"lga_code_2011":27630,"b60":null},"id":"lga_vic_crime_statistics_2012_2016.fid--38e292b1_16a853dde5d_-3718"}]}